.gitignore
.pre-commit-config.yaml
LICENSE
README.md
requirements.txt
script_requirements.txt
setup.cfg
setup.py
bugzilla_data/__init__.py
bugzilla_data/bz_data.py
bugzilla_data.egg-info/PKG-INFO
bugzilla_data.egg-info/SOURCES.txt
bugzilla_data.egg-info/dependency_links.txt
bugzilla_data.egg-info/requires.txt
bugzilla_data.egg-info/top_level.txt
conf/fixed_in_query.yaml
conf/query.yaml
images/example1.png
scripts/make_plot.py