Metadata-Version: 2.1
Name: bugzilla-data
Version: 0.0.5
Summary: Tools for plotting and gathering information about Bugzillas
Home-page: https://github.com/john-dupuy/bugzilla-data
Author: John Dupuy
Author-email: jdupuy@redhat.com
License: MIT
Keywords: bugzilla,plotting,data
Platform: UNKNOWN
Classifier: Development Status :: 3 - Alpha
Classifier: Environment :: Console
Classifier: Intended Audience :: Developers
Classifier: Operating System :: OS Independent
Classifier: Programming Language :: Python :: 3
Classifier: Programming Language :: Python :: 3.7
Classifier: Topic :: Utilities
